refuse/__init__.py
refuse/_high_header.py
refuse/_inventory.py
refuse/_refactor.py
refuse/high.py
refuse/low.py
refuse-0.0.4.dist-info/LICENSE
refuse-0.0.4.dist-info/METADATA
refuse-0.0.4.dist-info/WHEEL
refuse-0.0.4.dist-info/top_level.txt
refuse-0.0.4.dist-info/RECORD
