Metadata-Version: 2.1
Name: refuse
Version: 0.0.4
Summary: Simple cross-plattform ctypes bindings for libfuse / FUSE for macOS / WinFsp
Home-page: https://github.com/pleiszenburg/refuse
Author: Sebastian M. Ernst
Author-email: ernst@pleiszenburg.de
License: ISC
Download-URL: https://github.com/pleiszenburg/refuse/archive/v0.0.4.tar.gz
Keywords: fuse,libfuse
Platform: UNKNOWN
Classifier: Development Status :: 3 - Alpha
Classifier: Intended Audience :: Developers
Classifier: License :: OSI Approved :: ISC License (ISCL)
Classifier: Operating System :: MacOS
Classifier: Operating System :: POSIX
Classifier: Operating System :: POSIX :: BSD
Classifier: Operating System :: POSIX :: Linux
Classifier: Operating System :: Unix
Classifier: Operating System :: Microsoft :: Windows
Classifier: Programming Language :: Python :: 3
Classifier: Programming Language :: Python :: 3.5
Classifier: Programming Language :: Python :: 3.6
Classifier: Programming Language :: Python :: 3.7
Classifier: Programming Language :: Python :: 3.8
Classifier: Topic :: System :: Filesystems
Requires-Python: >=3.5
Provides-Extra: dev
Requires-Dist: coverage ; extra == 'dev'
Requires-Dist: pytest ; extra == 'dev'
Requires-Dist: python-language-server[all] ; extra == 'dev'
Requires-Dist: setuptools ; extra == 'dev'
Requires-Dist: Sphinx ; extra == 'dev'
Requires-Dist: sphinx-rtd-theme ; extra == 'dev'
Requires-Dist: twine ; extra == 'dev'
Requires-Dist: wheel ; extra == 'dev'
